basaran/__init__.py
basaran/__main__.py
basaran/choice.py
basaran/model.py
basaran/tokenizer.py
basaran/static/playground.css
basaran/static/playground.js
basaran/static/presets.json
basaran/templates/default.chat.jinja
basaran/templates/playground.html
basaran-0.21.1.data/scripts/download.py
basaran-0.21.1.data/scripts/render.py
basaran-0.21.1.dist-info/LICENSE
basaran-0.21.1.dist-info/METADATA
basaran-0.21.1.dist-info/WHEEL
basaran-0.21.1.dist-info/top_level.txt
basaran-0.21.1.dist-info/RECORD
