Metadata-Version: 2.1
Name: basaran
Version: 0.21.1
Summary: Open-source alternative to the OpenAI text completion API
Author: Hyperonym
Author-email: prompt@hyperonym.org
License: MIT
Keywords: api,huggingface,nlp,openai,transformer
Classifier: Development Status :: 4 - Beta
Classifier: Intended Audience :: Developers
Classifier: Intended Audience :: Education
Classifier: Intended Audience :: Science/Research
Classifier: License :: OSI Approved :: MIT License
Classifier: Operating System :: OS Independent
Classifier: Programming Language :: Python :: 3
Classifier: Programming Language :: Python :: 3.8
Classifier: Programming Language :: Python :: 3.9
Classifier: Programming Language :: Python :: 3.10
Classifier: Topic :: Scientific/Engineering :: Artificial Intelligence
Requires-Python: >=3.8.0
License-File: LICENSE
Requires-Dist: flask-cors
Requires-Dist: flask
Requires-Dist: jinja2
Requires-Dist: safetensors
Requires-Dist: scipy
Requires-Dist: torch
Requires-Dist: transformers
Requires-Dist: waitress
